koodousfinder/__init__.py
koodousfinder/client.py
koodousfinder/console.py
koodousfinder/response.py
koodousfinder-0.1.1.dist-info/METADATA
koodousfinder-0.1.1.dist-info/WHEEL
koodousfinder-0.1.1.dist-info/entry_points.txt
koodousfinder-0.1.1.dist-info/RECORD
