Metadata-Version: 2.1
Name: koodousfinder
Version: 0.1.1
Summary: A simple tool to allows users to search for and analyze android apps for potential security threats and vulnerabilities
Home-page: https://github.com/teixeira0xfffff/KoodousFinder
Author: teixeira0xfffff
Author-email: www@www.www
Requires-Python: >=3.7.2,<4.0
Classifier: Programming Language :: Python :: 3
Classifier: Programming Language :: Python :: 3.8
Classifier: Programming Language :: Python :: 3.9
Classifier: Programming Language :: Python :: 3.10
Classifier: Programming Language :: Python :: 3.11
Requires-Dist: keyring (>=23.13.1,<24.0.0)
Requires-Dist: pydantic (>=1.10.7,<2.0.0)
Requires-Dist: requests (>=2.28.2,<3.0.0)
Requires-Dist: stix2 (>=3.0.1,<4.0.0)
Project-URL: Repository, https://github.com/teixeira0xfffff/KoodousFinder
